{
  "name": "presence-sensor-esp32",
  "version": "2026.02.14015745",
  "home_assistant_domain": "esphome",
  "new_install_prompt_erase": true,
  "builds": [
    {
      "chipFamily": "ESP32",
      "parts": [
        {
          "path": "presence-sensor-esp32.factory.bin",
          "offset": 0,
          "md5": "c20c2d9c62532850cfc8af0ff1172e74"
        }
      ],
      "ota": {
        "path": "presence-sensor-esp32.ota.bin",
        "md5": "967a38e34c3988eb7d7fec7278e3ea6d"
      }
    }
  ]
}
